hawking/__init__.py
hawking/cli.py
hawking/bot/secretary/__init__.py
hawking/bot/secretary/secretary.py
hawking/bot/telegram/__init__.py
hawking/bot/telegram/bot.py
hawking/common/__init__.py
hawking/common/color.py
hawking/encoder/__init__.py
hawking/encoder/bert/__init__.py
hawking/encoder/bert/encoder.py
hawking/encoder/inceptionresnetv2/__init__.py
hawking/encoder/inceptionresnetv2/encoder.py
hawking/encoder/resnet50/__init__.py
hawking/encoder/resnet50/encoder.py
hawking/encoder/universal/__init__.py
hawking/encoder/universal/encoder.py
hawking/encoder/vgg/__init__.py
hawking/encoder/vgg/encoder.py
hawking/frontend/__init__.py
hawking/frontend/application.py
hawking/frontend/logging.conf
hawking/frontend/api/__init__.py
hawking/frontend/api/search.py
hawking/frontend/engine/__init__.py
hawking/frontend/engine/default.py
hawking/frontend/engine/local.py
hawking/frontend/engine/logging.conf
hawking/frontend/engine/online.py
hawking/frontend/store/__init__.py
hawking/frontend/store/default.py
hawking/index/__init__.py
hawking/index/faiss.py
hawking/queue/__init__.py
hawking/queue/local_queue.py
hawking/serve/__init__.py
hawking/serve/caption_server.py
hawking/serve/faiss_server.py
hawking/serve/queue_server.py
hawking/serve/run_codegen.py
hawking/serve/sptag_server.py
hawking/serve/store_server.py
hawking/sptag/.DS_Store
hawking/sptag/AnnClient.java
hawking/sptag/AnnIndex.java
hawking/sptag/BasicResult.java
hawking/sptag/JAVASPTAG.java
hawking/sptag/JAVASPTAGClient.java
hawking/sptag/JAVASPTAGClientJNI.java
hawking/sptag/JAVASPTAGJNI.java
hawking/sptag/README.md
hawking/sptag/SPTAG.py
hawking/sptag/SPTAGClient.py
hawking/sptag/_SPTAG.so
hawking/sptag/_SPTAGClient.so
hawking/sptag/__init__.py
hawking/sptag/aggregator
hawking/sptag/aggregator.ini
hawking/sptag/client
hawking/sptag/indexbuilder
hawking/sptag/indexsearcher
hawking/sptag/libSPTAGLib.a
hawking/sptag/nohup.out
hawking/sptag/python_test.py
hawking/sptag/random-docs-100-dim-10.em
hawking/sptag/server
hawking-0.1.63.dist-info/LICENSE
hawking-0.1.63.dist-info/METADATA
hawking-0.1.63.dist-info/WHEEL
hawking-0.1.63.dist-info/entry_points.txt
hawking-0.1.63.dist-info/top_level.txt
hawking-0.1.63.dist-info/RECORD
