Metadata-Version: 2.1
Name: hawking
Version: 0.1.63
Summary: Hawking CLI
Home-page: https://www.peach.co
Author: Peach Inc
Author-email: hi@peach.com
License: Apache License, Version 2.0
Keywords: hawking
Platform: UNKNOWN
Classifier: Development Status :: 3 - Alpha
Classifier: Intended Audience :: Developers
Classifier: Natural Language :: English
Classifier: Operating System :: POSIX :: Linux
Classifier: Programming Language :: Python :: 3.6
Classifier: License :: OSI Approved :: Apache Software License
Requires-Dist: Click (>=6.0)
Requires-Dist: bert-serving-server (>=1.9.6)
Requires-Dist: bert-serving-client (>=1.9.6)
Requires-Dist: flask
Requires-Dist: flask-restplus
Requires-Dist: faiss-cpu
Requires-Dist: numpy (>=1.16.4)
Requires-Dist: tensorflow (>=1.13)
Requires-Dist: tensorflow-hub (>=0.5.0)
Requires-Dist: google-cloud-storage
Requires-Dist: sentencepiece
Requires-Dist: tf-sentencepiece
Requires-Dist: pytorch-transformers
Requires-Dist: python-telegram-bot (>=12.0.0)
Requires-Dist: keras (>=2.2.5)
Requires-Dist: Pillow
Requires-Dist: malaya (==2.7.5.0)
Requires-Dist: gast (==0.2.2)
Requires-Dist: hawking-proto
Requires-Dist: twine
